cli/__init__.py
cli/main.py
cli/commands/__init__.py
cli/commands/diff.py
cli/commands/init.py
cli/commands/list_cmd.py
cli/commands/login.py
cli/commands/logout.py
cli/commands/new.py
cli/commands/pull.py
cli/commands/push.py
cli/commands/search.py
cli/commands/status.py
cli/commands/sync.py
cli/commands/user.py
cli/commands/vault_cmd.py
cli/utils/__init__.py
cli/utils/api.py
cli/utils/command_utils.py
cli/utils/config.py
cli/utils/hash_utils.py
cli/utils/token.py
cli/utils/vault_ignore.py
deeply_vault-0.2.4.dist-info/METADATA
deeply_vault-0.2.4.dist-info/WHEEL
deeply_vault-0.2.4.dist-info/entry_points.txt
deeply_vault-0.2.4.dist-info/RECORD
