Metadata-Version: 2.4
Name: deeply-vault
Version: 0.2.4
Summary: Deeply Vault CLI tool for managing environment variables
Project-URL: Homepage, https://github.com/deeplyinc/deeply-env-vault
Project-URL: Repository, https://github.com/deeplyinc/deeply-env-vault
Author-email: Joonho Lee <joon@deeply.co.kr>
License: MIT
Classifier: Development Status :: 4 - Beta
Classifier: Intended Audience :: Developers
Classifier: License :: OSI Approved :: MIT License
Classifier: Operating System :: OS Independent
Classifier: Programming Language :: Python :: 3
Classifier: Programming Language :: Python :: 3.12
Requires-Python: >=3.12
Requires-Dist: click>=8.1.3
Requires-Dist: cryptography
Requires-Dist: pyyaml>=6.0
Requires-Dist: requests>=2.28.0
Requires-Dist: rich>=13.0.0
